anawsutils/__init__.py
anawsutils/athena.py
anawsutils/ce.py
anawsutils/r53.py
anawsutils/s3.py
anawsutils/secretsmanager.py
anawsutils/ses.py
anawsutils/sns.py
anawsutils/ssm.py
anawsutils/sts.py
anawsutils/tools.py
anawsutils/dynamodb/__init__.py
anawsutils/dynamodb/ddb.py
anawsutils/dynamodb/table.py
anawsutils/ec2/__init__.py
anawsutils/ec2/flavors.py
anawsutils-0.1.5.dist-info/LICENSE
anawsutils-0.1.5.dist-info/METADATA
anawsutils-0.1.5.dist-info/WHEEL
anawsutils-0.1.5.dist-info/top_level.txt
anawsutils-0.1.5.dist-info/RECORD
